oasa_api/__init__.py
oasa_api/exceptions.py
oasa_api/models.py
oasa_api/oasa_api.py
oasa_api/rest_adapter.py
oasa_api-0.1.1.dist-info/LICENSE
oasa_api-0.1.1.dist-info/METADATA
oasa_api-0.1.1.dist-info/WHEEL
oasa_api-0.1.1.dist-info/top_level.txt
oasa_api-0.1.1.dist-info/RECORD
