Metadata-Version: 2.1
Name: oasa_api
Version: 0.1.1
Summary: This Python package provides a convenient wrapper to interact with the OASA S.A. (Athens Public Transport) API, allowing users to retrieve various information related to the public transport network in Athens, Greece.
Author-email: Romain DEROLLEPOT <romain.derollepot@univ-eiffel.fr>
License: MIT License
Project-URL: Repository, https://github.com/rderollepot/oasa_api.git
Keywords: API,data,public transport,Athens,timetables
Classifier: Programming Language :: Python :: 3
Classifier: License :: OSI Approved :: MIT License
Classifier: Operating System :: OS Independent
License-File: LICENSE
Requires-Dist: pandas
Requires-Dist: requests
